laketower/__about__.py
laketower/__init__.py
laketower/__main__.py
laketower/cli.py
laketower/config.py
laketower/py.typed
laketower/tables.py
laketower/web.py
laketower/static/.gitkeep
laketower/static/datatables.bundle.js
laketower/static/datatables.js
laketower/static/editor.bundle.js
laketower/static/editor.js
laketower/static/vendor/bootstrap/bootstrap.bundle.min.js
laketower/static/vendor/bootstrap-icons/bootstrap-icons.min.css
laketower/static/vendor/bootstrap-icons/fonts/bootstrap-icons.woff
laketower/static/vendor/bootstrap-icons/fonts/bootstrap-icons.woff2
laketower/static/vendor/datatables.net-bs5/dataTables.bootstrap5.css
laketower/static/vendor/datatables.net-columncontrol-bs5/columnControl.bootstrap5.min.css
laketower/static/vendor/halfmoon/halfmoon.min.css
laketower/static/vendor/halfmoon/halfmoon.modern.css
laketower/templates/_base.html
laketower/templates/index.html
laketower/templates/queries/view.html
laketower/templates/tables/_macros.html
laketower/templates/tables/history.html
laketower/templates/tables/import.html
laketower/templates/tables/index.html
laketower/templates/tables/query.html
laketower/templates/tables/statistics.html
laketower/templates/tables/view.html
laketower-0.6.8.dist-info/METADATA
laketower-0.6.8.dist-info/WHEEL
laketower-0.6.8.dist-info/entry_points.txt
laketower-0.6.8.dist-info/licenses/LICENSE
laketower-0.6.8.dist-info/RECORD
