Metadata-Version: 2.4
Name: laketower
Version: 0.6.8
Summary: Oversee your lakehouse
Project-URL: Repository, https://github.com/datalpia/laketower
Project-URL: Issues, https://github.com/datalpia/laketower/issues
Project-URL: Changelog, https://github.com/datalpia/laketower/blob/main/CHANGELOG.md
Author-email: Romain Clement <git@romain-clement.net>
License: Apache-2.0
License-File: LICENSE
Keywords: data,delta-lake,lakehouse,sql
Classifier: Development Status :: 2 - Pre-Alpha
Classifier: Intended Audience :: Developers
Classifier: Intended Audience :: End Users/Desktop
Classifier: Intended Audience :: Information Technology
Classifier: Intended Audience :: Other Audience
Classifier: Programming Language :: Python :: 3.10
Classifier: Programming Language :: Python :: 3.11
Classifier: Programming Language :: Python :: 3.12
Classifier: Programming Language :: Python :: 3.13
Classifier: Topic :: Database
Classifier: Topic :: Software Development
Classifier: Topic :: Utilities
Requires-Python: <3.14,>=3.10
Requires-Dist: bleach
Requires-Dist: deltalake<2,>=1
Requires-Dist: duckdb
Requires-Dist: fastapi
Requires-Dist: jinja2!=3.1.5,>=3
Requires-Dist: markdown
Requires-Dist: pyarrow!=19.0.0
Requires-Dist: pydantic-settings>=2
Requires-Dist: pydantic>=2
Requires-Dist: python-multipart
Requires-Dist: pyyaml
Requires-Dist: rich
Requires-Dist: sqlglot
Requires-Dist: tzdata
Requires-Dist: uvicorn
